fund_optimizer/__init__.py
fund_optimizer/core.py
fund_optimizer/utils.py
tests/__init__.py
tests/test_optimizer.py
fund_optimizer-0.1.0.dist-info/METADATA
fund_optimizer-0.1.0.dist-info/WHEEL
fund_optimizer-0.1.0.dist-info/top_level.txt
fund_optimizer-0.1.0.dist-info/RECORD
