Metadata-Version: 2.1
Name: fund-optimizer
Version: 0.1.0
Summary: A package for fund optimization using QUBO
Home-page: https://github.com/yourusername/fund_optimizer
Author: Your Name
Classifier: Programming Language :: Python :: 3
Classifier: License :: OSI Approved :: MIT License
Classifier: Operating System :: OS Independent
Requires-Python: >=3.7
Requires-Dist: numpy>=1.21.0
Requires-Dist: pandas>=1.3.0
